compora/__init__.py
compora/nb_prefix.py
compora/special_process.py
compora/standardize.py
compora/tokenize.py
ComPora-0.1.0.dist-info/LICENSE
ComPora-0.1.0.dist-info/METADATA
ComPora-0.1.0.dist-info/WHEEL
ComPora-0.1.0.dist-info/entry_points.txt
ComPora-0.1.0.dist-info/top_level.txt
ComPora-0.1.0.dist-info/RECORD
